<?xml version="1.0" encoding="UTF-8"?>
<actions>
        <action>
            <actionName>run</actionName>
            <packagings>
                <packaging>jar</packaging>
            </packagings>
            <goals>
                <goal>process-classes</goal>
                <goal>org.codehaus.mojo:exec-maven-plugin:1.2.1:exec</goal>
            </goals>
            <properties>
                <exec.args>-classpath %classpath dumptspacket.Main -filename "H:\_D20160321161346P21020T90C101.ts" -l 100000 -p 12 26 27</exec.args>
                <exec.executable>java</exec.executable>
            </properties>
        </action>
        <action>
            <actionName>debug</actionName>
            <packagings>
                <packaging>jar</packaging>
            </packagings>
            <goals>
                <goal>process-classes</goal>
                <goal>org.codehaus.mojo:exec-maven-plugin:1.2.1:exec</goal>
            </goals>
            <properties>
                <exec.args>-Xdebug -Xrunjdwp:transport=dt_socket,server=n,address=${jpda.address} -classpath %classpath dumptspacket.Main -filename "H:\_D20160321161346P21020T90C101.ts" -l 100000 -p 12 26 27</exec.args>
                <exec.executable>java</exec.executable>
                <jpda.listen>true</jpda.listen>
            </properties>
        </action>
        <action>
            <actionName>profile</actionName>
            <packagings>
                <packaging>jar</packaging>
            </packagings>
            <goals>
                <goal>process-classes</goal>
                <goal>org.codehaus.mojo:exec-maven-plugin:1.2.1:exec</goal>
            </goals>
            <properties>
                <exec.args>-classpath %classpath dumptspacket.Main -filename "H:\_D20160321161346P21020T90C101.ts" -l 100000 -p 12 26 27</exec.args>
                <exec.executable>java</exec.executable>
            </properties>
        </action>
    </actions>
